<annotation>
	<folder>images</folder>
	<filename>B(13).jpg</filename>
	<path>F:\ml\test1\SMOKEDATA\images\B(13).jpg</path>
	<source>
		<database>Unknown</database>
	</source>
	<size>
		<width>720</width>
		<height>1280</height>
		<depth>1</depth>
	</size>
	<segmented>0</segmented>
	<object>
		<name>smoke</name>
		<pose>Unspecified</pose>
		<truncated>0</truncated>
		<difficult>0</difficult>
		<bndbox>
			<xmin>26</xmin>
			<ymin>716</ymin>
			<xmax>296</xmax>
			<ymax>807</ymax>
		</bndbox>
	</object>
</annotation>
